setup.py
aws/__init__.py
aws/main.py
aws.egg-info/PKG-INFO
aws.egg-info/SOURCES.txt
aws.egg-info/dependency_links.txt
aws.egg-info/entry_points.txt
aws.egg-info/not-zip-safe
aws.egg-info/requires.txt
aws.egg-info/top_level.txt
aws/libaws/__init__.py
aws/libaws/conf.py
aws/libaws/ec2.py
aws/libaws/elb.py
aws/libaws/service.py